setup.py
easy_distributions_dm/Binomialdistribution.py
easy_distributions_dm/Gaussiandistribution.py
easy_distributions_dm/Generaldistribution.py
easy_distributions_dm/__init__.py
easy_distributions_dm.egg-info/PKG-INFO
easy_distributions_dm.egg-info/SOURCES.txt
easy_distributions_dm.egg-info/dependency_links.txt
easy_distributions_dm.egg-info/not-zip-safe
easy_distributions_dm.egg-info/top_level.txt