Metadata-Version: 1.0
Name: easy-distributions-dm
Version: 2.0
Summary: Gaussian and Binomial distributions
Home-page: UNKNOWN
Author: Delong Meng
Author-email: delongmeng@hotmail.com
License: UNKNOWN
Platform: UNKNOWN
